multiapp_packager/__init__.py
multiapp_packager/__main__.py
multiapp_packager/app_info.py
multiapp_packager/cli.py
multiapp_packager/config_parser.py
multiapp_packager/packager.py
multiapp_packager-1.0.3.dist-info/METADATA
multiapp_packager-1.0.3.dist-info/WHEEL
multiapp_packager-1.0.3.dist-info/entry_points.txt
multiapp_packager-1.0.3.dist-info/RECORD
