Metadata-Version: 2.4
Name: multiapp-packager
Version: 1.0.3
Summary: 一个基于配置文件的模块化多应用打包工具
Project-URL: Homepage, https://github.com/yourusername/multiapp-packager
Project-URL: Documentation, https://github.com/yourusername/multiapp-packager/blob/main/README.md
Project-URL: Repository, https://github.com/yourusername/multiapp-packager
Project-URL: Issues, https://github.com/yourusername/multiapp-packager/issues
Author-email: Your Name <your.email@example.com>
License: MIT
Keywords: embedded,firmware,multiapp,packaging
Classifier: Development Status :: 4 - Beta
Classifier: Intended Audience :: Developers
Classifier: License :: OSI Approved :: MIT License
Classifier: Programming Language :: Python :: 3
Classifier: Programming Language :: Python :: 3.8
Classifier: Programming Language :: Python :: 3.9
Classifier: Programming Language :: Python :: 3.10
Classifier: Programming Language :: Python :: 3.11
Classifier: Programming Language :: Python :: 3.12
Classifier: Topic :: Software Development :: Build Tools
Classifier: Topic :: System :: Archiving :: Packaging
Requires-Python: >=3.8
Requires-Dist: pyyaml>=5.1
Provides-Extra: dev
Requires-Dist: black>=23.0; extra == 'dev'
Requires-Dist: flake8>=6.0; extra == 'dev'
Requires-Dist: pytest-cov>=4.0; extra == 'dev'
Requires-Dist: pytest>=7.0; extra == 'dev'
